nefesi/__init__.py
nefesi/class_index.py
nefesi/color_index.py
nefesi/layer_data.py
nefesi/network_data.py
nefesi/neuron_data.py
nefesi/neuron_feature.py
nefesi/orientation_index.py
nefesi/read_activations.py
nefesi/similarity_index.py
nefesi/symmetry_index.py
nefesi/test_orientation_idx.py
nefesi/test_vgg16.py
nefesi/tvgg16_1.py
nefesi/external/LRN.py
nefesi/external/__init__.py
nefesi/external/config.py
nefesi/external/model.py
nefesi/utils/__init__.py
nefesi/utils/image.py
nefesi/utils/plotting.py
nefesi-1.0.4.dist-info/METADATA
nefesi-1.0.4.dist-info/RECORD
nefesi-1.0.4.dist-info/WHEEL
nefesi-1.0.4.dist-info/top_level.txt
