Metadata-Version: 2.1
Name: nefesi
Version: 1.0.4
Summary: CNN analysis
Home-page: https://github.com/ramonbal/NEFESI
Author: oprades
Author-email: oskarpras@gmail.com
License: GNU
Platform: UNKNOWN
Requires-Dist: tensorflow (>=1.1.0)
Requires-Dist: keras (>=2.0.6)
Requires-Dist: numpy (>=1.13.1)
Requires-Dist: scipy (>=0.19.1)
